django_openpay/__init__.py
django_openpay/admin.py
django_openpay/apps.py
django_openpay/decorators.py
django_openpay/exceptions.py
django_openpay/hardcode.py
django_openpay/models.py
django_openpay/tasks.py
django_openpay/tests.py
django_openpay/urls.py
django_openpay/utils.py
django_openpay/views.py
django_openpay/webhooks.py
django_openpay/management/commands/__init__.py
django_openpay/management/commands/openpaysync.py
django_openpay/migrations/__init__.py
django_openpay-1.1.8.dist-info/DESCRIPTION.rst
django_openpay-1.1.8.dist-info/LICENSE.txt
django_openpay-1.1.8.dist-info/METADATA
django_openpay-1.1.8.dist-info/RECORD
django_openpay-1.1.8.dist-info/WHEEL
django_openpay-1.1.8.dist-info/metadata.json
django_openpay-1.1.8.dist-info/top_level.txt
testing/__init__.py
testing/celery.py
testing/manage.py
testing/settings.py
testing/urls.py
testing/wsgi.py
