Metadata-Version: 2.0
Name: django-openpay
Version: 1.1.8
Summary: Django application which integrates the OpenPay libraries for online transactions
Home-page: https://github.com/grvty-labs/django-openpay
Author: GRVTYlabs
Author-email: daniel.ortiz@grvtylabs.com
License: MIT
Platform: UNKNOWN
Classifier: Development Status :: 3 - Alpha
Classifier: Environment :: Web Environment
Classifier: Intended Audience :: Developers
Classifier: License :: OSI Approved :: BSD License
Classifier: Operating System :: OS Independent
Classifier: Programming Language :: Python :: 3.2
Classifier: Programming Language :: Python :: 3.3
Classifier: Programming Language :: Python :: 3.4
Classifier: Programming Language :: Python :: 3.5
Classifier: Framework :: Django
Requires-Dist: jsonfield
Requires-Dist: OpenpayGrvty (>=0.4.7)
